medgeconv/__init__.py
medgeconv/appli.py
medgeconv/layers.py
medgeconv/util.py
medgeconv/legacy/__init__.py
medgeconv/legacy/layers.py
medgeconv/legacy/util.py
medgeconv/tf_ops/Makefile
medgeconv/tf_ops/__init__.py
medgeconv/tf_ops/compile.sh
medgeconv/tf_ops/cc/kernels/knn_graph.h
medgeconv/tf_ops/cc/kernels/knn_graph_kernels.cc
medgeconv/tf_ops/cc/kernels/knn_graph_kernels.cu
medgeconv/tf_ops/cc/ops/knn_graph_ops.cc
medgeconv/tf_ops/python/__init__.py
medgeconv/tf_ops/python/ops/__init__.py
medgeconv/tf_ops/python/ops/_knn_graph_ops.so
medgeconv/tf_ops/python/ops/knn_graph_ops.py
medgeconv-2.2.dist-info/LICENSE
medgeconv-2.2.dist-info/METADATA
medgeconv-2.2.dist-info/WHEEL
medgeconv-2.2.dist-info/top_level.txt
medgeconv-2.2.dist-info/RECORD
