Metadata-Version: 2.1
Name: medgeconv
Version: 2.2
Summary: UNKNOWN
Home-page: UNKNOWN
Author: Stefan Reck
Author-email: stefan.reck@fau.de
License: MIT
Platform: UNKNOWN
License-File: LICENSE
Requires-Dist: numpy
Requires-Dist: tensorflow (==2.7.*)
